CHANGES.txt
CONTRIBUTORS.txt
MANIFEST.in
README.txt
bootstrap.py
buildout.cfg
setup.cfg
setup.py
collective/__init__.py
collective.sphinx.includedoc.egg-info/PKG-INFO
collective.sphinx.includedoc.egg-info/SOURCES.txt
collective.sphinx.includedoc.egg-info/dependency_links.txt
collective.sphinx.includedoc.egg-info/namespace_packages.txt
collective.sphinx.includedoc.egg-info/not-zip-safe
collective.sphinx.includedoc.egg-info/requires.txt
collective.sphinx.includedoc.egg-info/top_level.txt
collective/sphinx/__init__.py
collective/sphinx/includedoc/__init__.py