Metadata-Version: 1.0
Name: collective.sphinx.includedoc
Version: 0.2
Summary: Sphinx extension for including doctests
Home-page: http://svn.plone.org/svn/collective/collective.sphinx.includedoc
Author: Rok Garbas
Author-email: rok@garbas.si
License: GPL
Keywords: zope archetypes sphinx documentation
Platform: UNKNOWN
Classifier: Intended Audience :: Developers
Classifier: Programming Language :: Python
Classifier: License :: OSI Approved :: GNU General Public License (GPL)
